{
    "defs": [
        {
            "kind": "class",
            "word": "TimeIt",
            "parentName": null,
            "type": "ClassDeclaration",
            "body": [
                {
                    "kind": "constructor",
                    "word": "constructor",
                    "static": false,
                    "computed": false,
                    "is_symbol": false,
                    "value": {
                        "type": "FunctionExpression",
                        "id": null,
                        "generator": false,
                        "expression": false,
                        "async": false,
                        "params": [
                            {
                                "name": "label"
                            },
                            {
                                "name": "startNow",
                                "default_value": false
                            }
                        ],
                        "pos": {
                            "start": 548,
                            "end": 702,
                            "loc": {
                                "start": {
                                    "line": 23,
                                    "column": 15
                                },
                                "end": {
                                    "line": 29,
                                    "column": 5
                                }
                            }
                        }
                    },
                    "type": "MethodDefinition",
                    "comments": {
                        "header": [],
                        "inner": []
                    },
                    "pos": {
                        "start": 537,
                        "end": 702,
                        "loc": {
                            "start": {
                                "line": 23,
                                "column": 4
                            },
                            "end": {
                                "line": 29,
                                "column": 5
                            }
                        }
                    }
                },
                {
                    "kind": "method",
                    "word": "stringLabel",
                    "static": false,
                    "computed": false,
                    "is_symbol": false,
                    "value": {
                        "type": "FunctionExpression",
                        "id": null,
                        "generator": false,
                        "expression": false,
                        "async": false,
                        "params": [],
                        "pos": {
                            "start": 721,
                            "end": 816,
                            "loc": {
                                "start": {
                                    "line": 31,
                                    "column": 15
                                },
                                "end": {
                                    "line": 34,
                                    "column": 5
                                }
                            }
                        }
                    },
                    "type": "MethodDefinition",
                    "comments": {
                        "header": [],
                        "inner": []
                    },
                    "pos": {
                        "start": 710,
                        "end": 816,
                        "loc": {
                            "start": {
                                "line": 31,
                                "column": 4
                            },
                            "end": {
                                "line": 34,
                                "column": 5
                            }
                        }
                    }
                },
                {
                    "kind": "method",
                    "word": "stamp",
                    "static": false,
                    "computed": false,
                    "is_symbol": false,
                    "value": {
                        "type": "FunctionExpression",
                        "id": null,
                        "generator": false,
                        "expression": false,
                        "async": false,
                        "params": [],
                        "pos": {
                            "start": 829,
                            "end": 868,
                            "loc": {
                                "start": {
                                    "line": 36,
                                    "column": 9
                                },
                                "end": {
                                    "line": 38,
                                    "column": 5
                                }
                            }
                        }
                    },
                    "type": "MethodDefinition",
                    "comments": {
                        "header": [],
                        "inner": []
                    },
                    "pos": {
                        "start": 824,
                        "end": 868,
                        "loc": {
                            "start": {
                                "line": 36,
                                "column": 4
                            },
                            "end": {
                                "line": 38,
                                "column": 5
                            }
                        }
                    }
                },
                {
                    "kind": "method",
                    "word": "start",
                    "static": false,
                    "computed": false,
                    "is_symbol": false,
                    "value": {
                        "type": "FunctionExpression",
                        "id": null,
                        "generator": false,
                        "expression": false,
                        "async": false,
                        "params": [],
                        "pos": {
                            "start": 881,
                            "end": 978,
                            "loc": {
                                "start": {
                                    "line": 40,
                                    "column": 9
                                },
                                "end": {
                                    "line": 44,
                                    "column": 5
                                }
                            }
                        }
                    },
                    "type": "MethodDefinition",
                    "comments": {
                        "header": [],
                        "inner": []
                    },
                    "pos": {
                        "start": 876,
                        "end": 978,
                        "loc": {
                            "start": {
                                "line": 40,
                                "column": 4
                            },
                            "end": {
                                "line": 44,
                                "column": 5
                            }
                        }
                    }
                },
                {
                    "kind": "method",
                    "word": "stop",
                    "static": false,
                    "computed": false,
                    "is_symbol": false,
                    "value": {
                        "type": "FunctionExpression",
                        "id": null,
                        "generator": false,
                        "expression": false,
                        "async": false,
                        "params": [],
                        "pos": {
                            "start": 990,
                            "end": 1140,
                            "loc": {
                                "start": {
                                    "line": 46,
                                    "column": 8
                                },
                                "end": {
                                    "line": 51,
                                    "column": 5
                                }
                            }
                        }
                    },
                    "type": "MethodDefinition",
                    "comments": {
                        "header": [],
                        "inner": []
                    },
                    "pos": {
                        "start": 986,
                        "end": 1140,
                        "loc": {
                            "start": {
                                "line": 46,
                                "column": 4
                            },
                            "end": {
                                "line": 51,
                                "column": 5
                            }
                        }
                    }
                },
                {
                    "kind": "method",
                    "word": "timeTaken",
                    "static": false,
                    "computed": false,
                    "is_symbol": false,
                    "value": {
                        "type": "FunctionExpression",
                        "id": null,
                        "generator": false,
                        "expression": false,
                        "async": false,
                        "params": [],
                        "pos": {
                            "start": 1157,
                            "end": 1439,
                            "loc": {
                                "start": {
                                    "line": 53,
                                    "column": 13
                                },
                                "end": {
                                    "line": 65,
                                    "column": 5
                                }
                            }
                        }
                    },
                    "type": "MethodDefinition",
                    "comments": {
                        "header": [],
                        "inner": []
                    },
                    "pos": {
                        "start": 1148,
                        "end": 1439,
                        "loc": {
                            "start": {
                                "line": 53,
                                "column": 4
                            },
                            "end": {
                                "line": 65,
                                "column": 5
                            }
                        }
                    }
                },
                {
                    "kind": "method",
                    "word": "reset",
                    "static": false,
                    "computed": false,
                    "is_symbol": false,
                    "value": {
                        "type": "FunctionExpression",
                        "id": null,
                        "generator": false,
                        "expression": false,
                        "async": false,
                        "params": [],
                        "pos": {
                            "start": 1452,
                            "end": 1551,
                            "loc": {
                                "start": {
                                    "line": 67,
                                    "column": 9
                                },
                                "end": {
                                    "line": 71,
                                    "column": 5
                                }
                            }
                        }
                    },
                    "type": "MethodDefinition",
                    "comments": {
                        "header": [],
                        "inner": []
                    },
                    "pos": {
                        "start": 1447,
                        "end": 1551,
                        "loc": {
                            "start": {
                                "line": 67,
                                "column": 4
                            },
                            "end": {
                                "line": 71,
                                "column": 5
                            }
                        }
                    }
                },
                {
                    "kind": "get",
                    "word": "value",
                    "static": false,
                    "computed": false,
                    "is_symbol": false,
                    "value": {
                        "type": "FunctionExpression",
                        "id": null,
                        "generator": false,
                        "expression": false,
                        "async": false,
                        "params": [],
                        "pos": {
                            "start": 1568,
                            "end": 1612,
                            "loc": {
                                "start": {
                                    "line": 73,
                                    "column": 13
                                },
                                "end": {
                                    "line": 75,
                                    "column": 5
                                }
                            }
                        }
                    },
                    "type": "MethodDefinition",
                    "comments": {
                        "header": [],
                        "inner": []
                    },
                    "pos": {
                        "start": 1559,
                        "end": 1612,
                        "loc": {
                            "start": {
                                "line": 73,
                                "column": 4
                            },
                            "end": {
                                "line": 75,
                                "column": 5
                            }
                        }
                    }
                },
                {
                    "kind": "method",
                    "word": "runningString",
                    "static": false,
                    "computed": false,
                    "is_symbol": false,
                    "value": {
                        "type": "FunctionExpression",
                        "id": null,
                        "generator": false,
                        "expression": false,
                        "async": false,
                        "params": [],
                        "pos": {
                            "start": 1633,
                            "end": 1842,
                            "loc": {
                                "start": {
                                    "line": 77,
                                    "column": 17
                                },
                                "end": {
                                    "line": 87,
                                    "column": 5
                                }
                            }
                        }
                    },
                    "type": "MethodDefinition",
                    "comments": {
                        "header": [],
                        "inner": []
                    },
                    "pos": {
                        "start": 1620,
                        "end": 1842,
                        "loc": {
                            "start": {
                                "line": 77,
                                "column": 4
                            },
                            "end": {
                                "line": 87,
                                "column": 5
                            }
                        }
                    }
                },
                {
                    "kind": "method",
                    "word": "toString",
                    "static": false,
                    "computed": false,
                    "is_symbol": false,
                    "value": {
                        "type": "FunctionExpression",
                        "id": null,
                        "generator": false,
                        "expression": false,
                        "async": false,
                        "params": [],
                        "pos": {
                            "start": 1858,
                            "end": 1949,
                            "loc": {
                                "start": {
                                    "line": 89,
                                    "column": 12
                                },
                                "end": {
                                    "line": 91,
                                    "column": 5
                                }
                            }
                        }
                    },
                    "type": "MethodDefinition",
                    "comments": {
                        "header": [],
                        "inner": []
                    },
                    "pos": {
                        "start": 1850,
                        "end": 1949,
                        "loc": {
                            "start": {
                                "line": 89,
                                "column": 4
                            },
                            "end": {
                                "line": 91,
                                "column": 5
                            }
                        }
                    }
                },
                {
                    "kind": "method",
                    "word": "Symbol.toPrimitive",
                    "static": false,
                    "computed": true,
                    "is_symbol": true,
                    "value": {
                        "type": "FunctionExpression",
                        "id": null,
                        "generator": false,
                        "expression": false,
                        "async": false,
                        "params": [
                            {
                                "name": "hint"
                            }
                        ],
                        "pos": {
                            "start": 1977,
                            "end": 2308,
                            "loc": {
                                "start": {
                                    "line": 93,
                                    "column": 24
                                },
                                "end": {
                                    "line": 108,
                                    "column": 5
                                }
                            }
                        }
                    },
                    "type": "MethodDefinition",
                    "comments": {
                        "header": [],
                        "inner": [
                            {
                                "text": " return this.value;",
                                "block": false,
                                "line": 95
                            }
                        ]
                    },
                    "pos": {
                        "start": 1957,
                        "end": 2308,
                        "loc": {
                            "start": {
                                "line": 93,
                                "column": 4
                            },
                            "end": {
                                "line": 108,
                                "column": 5
                            }
                        }
                    }
                }
            ],
            "comments": {
                "header": [
                    {
                        "text": "\r\n---\r\ntitle: TimeIt Class\r\n---\r\nThe TimeIt entity provides _time taken_ tests for running code.\r\n\r\n    const timeit = new TimeIt('my label')\r\n    timeit.start()\r\n    // ... insert delay ...\r\n    timeit.stop()\r\n    timeit.timeTaken()\r\n    // TimeIt(\"my label\") complete 100ms\r\n\r\nThis can be reduced to two statements, by assigning a `startNow` bool\r\nto the constructor:\r\n\r\n    const timeit = new TimeIt('my label', true)\r\n    console.log(timeit.stop().toString())\r\n    // TimeIt(\"my label\") complete 2002ms\r\n\r\n ",
                        "block": true,
                        "line": 21
                    }
                ],
                "inner": [
                    {
                        "text": " return this.value;",
                        "block": false,
                        "line": 95
                    }
                ]
            },
            "pos": {
                "start": 517,
                "end": 2313,
                "loc": {
                    "start": {
                        "line": 22,
                        "column": 0
                    },
                    "end": {
                        "line": 110,
                        "column": 1
                    }
                }
            }
        },
        {
            "type": "ExpressionStatement",
            "expression": {
                "type": "CallExpression",
                "start": 2319,
                "end": 2349,
                "loc": {
                    "start": {
                        "line": 113,
                        "column": 0
                    },
                    "end": {
                        "line": 113,
                        "column": 30
                    }
                },
                "callee": {
                    "type": "MemberExpression",
                    "start": 2319,
                    "end": 2341,
                    "loc": {
                        "start": {
                            "line": 113,
                            "column": 0
                        },
                        "end": {
                            "line": 113,
                            "column": 22
                        }
                    },
                    "object": {
                        "type": "MemberExpression",
                        "start": 2319,
                        "end": 2333,
                        "loc": {
                            "start": {
                                "line": 113,
                                "column": 0
                            },
                            "end": {
                                "line": 113,
                                "column": 14
                            }
                        },
                        "object": {
                            "type": "Identifier",
                            "start": 2319,
                            "end": 2328,
                            "loc": {
                                "start": {
                                    "line": 113,
                                    "column": 0
                                },
                                "end": {
                                    "line": 113,
                                    "column": 9
                                }
                            },
                            "name": "Polypoint",
                            "pos": {
                                "start": 2319,
                                "end": 2328,
                                "loc": {
                                    "start": {
                                        "line": 113,
                                        "column": 0
                                    },
                                    "end": {
                                        "line": 113,
                                        "column": 9
                                    }
                                }
                            }
                        },
                        "property": {
                            "type": "Identifier",
                            "start": 2329,
                            "end": 2333,
                            "loc": {
                                "start": {
                                    "line": 113,
                                    "column": 10
                                },
                                "end": {
                                    "line": 113,
                                    "column": 14
                                }
                            },
                            "name": "head",
                            "pos": {
                                "start": 2329,
                                "end": 2333,
                                "loc": {
                                    "start": {
                                        "line": 113,
                                        "column": 10
                                    },
                                    "end": {
                                        "line": 113,
                                        "column": 14
                                    }
                                }
                            }
                        },
                        "computed": false,
                        "optional": false,
                        "pos": {
                            "start": 2319,
                            "end": 2333,
                            "loc": {
                                "start": {
                                    "line": 113,
                                    "column": 0
                                },
                                "end": {
                                    "line": 113,
                                    "column": 14
                                }
                            }
                        }
                    },
                    "property": {
                        "type": "Identifier",
                        "start": 2334,
                        "end": 2341,
                        "loc": {
                            "start": {
                                "line": 113,
                                "column": 15
                            },
                            "end": {
                                "line": 113,
                                "column": 22
                            }
                        },
                        "name": "install",
                        "pos": {
                            "start": 2334,
                            "end": 2341,
                            "loc": {
                                "start": {
                                    "line": 113,
                                    "column": 15
                                },
                                "end": {
                                    "line": 113,
                                    "column": 22
                                }
                            }
                        }
                    },
                    "computed": false,
                    "optional": false,
                    "pos": {
                        "start": 2319,
                        "end": 2341,
                        "loc": {
                            "start": {
                                "line": 113,
                                "column": 0
                            },
                            "end": {
                                "line": 113,
                                "column": 22
                            }
                        }
                    }
                },
                "arguments": [
                    {
                        "type": "Identifier",
                        "start": 2342,
                        "end": 2348,
                        "loc": {
                            "start": {
                                "line": 113,
                                "column": 23
                            },
                            "end": {
                                "line": 113,
                                "column": 29
                            }
                        },
                        "name": "TimeIt",
                        "pos": {
                            "start": 2342,
                            "end": 2348,
                            "loc": {
                                "start": {
                                    "line": 113,
                                    "column": 23
                                },
                                "end": {
                                    "line": 113,
                                    "column": 29
                                }
                            }
                        }
                    }
                ],
                "optional": false,
                "pos": {
                    "start": 2319,
                    "end": 2349,
                    "loc": {
                        "start": {
                            "line": 113,
                            "column": 0
                        },
                        "end": {
                            "line": 113,
                            "column": 30
                        }
                    }
                }
            },
            "pos": {
                "start": 2319,
                "end": 2349,
                "loc": {
                    "start": {
                        "line": 113,
                        "column": 0
                    },
                    "end": {
                        "line": 113,
                        "column": 30
                    }
                }
            }
        }
    ],
    "types": [
        "ClassDeclaration",
        "ExpressionStatement"
    ],
    "info": {
        "filename": "timeit.js",
        "path": "/workspaces/polypoint/point_src/timeit.js",
        "size": 2349,
        "parsed_date": "2025-11-02T21:11:41.922Z"
    }
}