{
    "defs": [
        {
            "kind": "function",
            "word": "quantizeNumber",
            "generator": false,
            "expression": false,
            "async": false,
            "params": [
                {
                    "name": "value"
                },
                {
                    "name": "quantize",
                    "default_value": 1
                }
            ],
            "id": {
                "type": "Identifier",
                "start": 11,
                "end": 25,
                "loc": {
                    "start": {
                        "line": 2,
                        "column": 9
                    },
                    "end": {
                        "line": 2,
                        "column": 23
                    }
                },
                "name": "quantizeNumber",
                "pos": {
                    "start": 11,
                    "end": 25,
                    "loc": {
                        "start": {
                            "line": 2,
                            "column": 9
                        },
                        "end": {
                            "line": 2,
                            "column": 23
                        }
                    }
                }
            },
            "pos": {
                "start": 2,
                "end": 142,
                "loc": {
                    "start": {
                        "line": 2,
                        "column": 0
                    },
                    "end": {
                        "line": 5,
                        "column": 1
                    }
                }
            },
            "type": "FunctionDeclaration"
        }
    ],
    "types": [
        "FunctionDeclaration"
    ],
    "info": {
        "filename": "quantize.js",
        "path": "C:\\Users\\jay\\Documents\\projects\\polypoint\\point_src\\functions\\quantize.js",
        "size": 142,
        "parsed_date": "2026-06-20T01:22:57.146Z"
    }
}